memedb/__init__.py
memedb/memedb.py
memedb-0.1.0.dist-info/METADATA
memedb-0.1.0.dist-info/WHEEL
memedb-0.1.0.dist-info/RECORD
