Metadata-Version: 2.1
Name: memedb
Version: 0.1.0
Summary: MemeDB - the fun and quirky side project for data storage, because sometimes it's good to take a break from the serious stuff!
License: MIT
Author: Vahid Al
Author-email: thevahidal@gmail.com
Requires-Python: >=3.10,<4.0
Classifier: License :: OSI Approved :: MIT License
Classifier: Programming Language :: Python :: 3
Classifier: Programming Language :: Python :: 3.10
Classifier: Programming Language :: Python :: 3.11
